laudanum/__init__.py
laudanum/cli.py
laudanum/exceptions.py
laudanum/fonts/DejaVuSansMono-Bold.ttf
laudanum/fonts/DejaVuSansMono-BoldOblique.ttf
laudanum/fonts/DejaVuSansMono-Oblique.ttf
laudanum/fonts/DejaVuSansMono.ttf
laudanum/logo.py
laudanum/validators.py
laudanum-0.1.11.dist-info/LICENSE
laudanum-0.1.11.dist-info/METADATA
laudanum-0.1.11.dist-info/WHEEL
laudanum-0.1.11.dist-info/entry_points.txt
laudanum-0.1.11.dist-info/RECORD
