Metadata-Version: 2.3
Name: laudanum
Version: 0.1.11
Summary: A CLI tool for creating logos with ASCII art.
License: MIT
Keywords: ascii,art,logo,image
Author: Mike Letts
Author-email: lettsmt@gmail.com
Maintainer: Mike Letts
Maintainer-email: lettsmt@gmail.com
Requires-Python: >=3.9
Classifier: License :: OSI Approved :: MIT License
Classifier: Programming Language :: Python :: 3
Classifier: Programming Language :: Python :: 3.9
Classifier: Programming Language :: Python :: 3.10
Classifier: Programming Language :: Python :: 3.11
Classifier: Programming Language :: Python :: 3.12
Classifier: Programming Language :: Python :: 3.13
Requires-Dist: art (>=6.5,<7.0)
Requires-Dist: attrs (>=25.3.0,<26.0.0)
Requires-Dist: click (>=8.1.8,<9.0.0)
Requires-Dist: pillow (>=11.2.1,<12.0.0)
Requires-Dist: rich (>=14.0.0,<15.0.0)
